published/__init__.py
published/published.py
published-0.1.1.dist-info/LICENSE
published-0.1.1.dist-info/METADATA
published-0.1.1.dist-info/WHEEL
published-0.1.1.dist-info/top_level.txt
published-0.1.1.dist-info/RECORD
