Metadata-Version: 2.1
Name: published
Version: 0.1.1
Summary: Python library that serves as an example/template for a package publishing guide.
Home-page: https://github.com/python-supply/published
Author: Python Supply
Author-email: contact@python.supply
License: MIT
Platform: UNKNOWN
